{
  "total": 632,
  "by_type": {
    "研究论文": 525,
    "综述": 44,
    "案例报告": 24,
    "Benchmark": 15,
    "系统综述/Meta分析": 10,
    "其他": 7,
    "临床试验": 7
  },
  "by_year": {
    "2026": 598,
    "2025": 34
  },
  "top_journals": {
    "Frontiers in microbiology": 33,
    "Frontiers in cellular and infection microbiology": 31,
    "Microbiology spectrum": 24,
    "Scientific reports": 21,
    "mSystems": 13,
    "Journal of hazardous materials": 13,
    "Microbiome": 12,
    "Nucleic acids research": 12,
    "International journal of infectious diseases : IJID : official publication of the International Society for Infectious Diseases": 11,
    "Poultry science": 9,
    "Gut microbes": 9,
    "Bioresource technology": 8,
    "Diagnostic microbiology and infectious disease": 7,
    "Frontiers in veterinary science": 7,
    "Microbial pathogenesis": 6,
    "Nutrients": 6,
    "Water research": 6,
    "NPJ biofilms and microbiomes": 5,
    "Nature communications": 5,
    "Applied and environmental microbiology": 5
  },
  "top_diseases": {
    "结直肠癌": 5,
    "血流感染": 4,
    "帕金森病": 4,
    "肥胖": 4,
    "溃疡性结肠炎": 3,
    "炎症性肠病": 3,
    "下呼吸道感染": 3,
    "食管鳞状细胞癌": 3,
    "中枢神经系统感染": 3,
    "腹泻": 3,
    "呼吸道感染": 3,
    "哮喘": 3,
    "重症肺炎": 2,
    "高尿酸血症肾病": 2,
    "牛呼吸道疾病（BRD）": 2,
    "自闭症谱系障碍": 2,
    "系统性红斑狼疮（SLE）": 2,
    "糖尿病足骨髓炎": 2,
    "2型糖尿病": 2,
    "囊性纤维化": 2
  }
}